alej_supl/__init__.py
alej_supl/__main__.py
alej_supl/classes.py
alej_supl/functions.py
alej_supl-1.2.dist-info/LICENSE
alej_supl-1.2.dist-info/METADATA
alej_supl-1.2.dist-info/WHEEL
alej_supl-1.2.dist-info/top_level.txt
alej_supl-1.2.dist-info/RECORD
