Metadata-Version: 2.1
Name: alej-supl
Version: 1.2
Summary: A very simple cli program that shows supplementation for Gymnazium Nad Aleji school
Home-page: https://github.com/kockahonza/alej_supl
Author: UNKNOWN
Author-email: UNKNOWN
License: UNKNOWN
Platform: UNKNOWN
